{
  "openrpc": "1.3.2",
  "info": {
    "title": "Actions",
    "version": "0.1.0"
  },
  "methods": [
    {
      "name": "insert",
      "params": [
        {
          "$ref": "#/components/params/uri"
        },
        {
          "$ref": "#/components/params/params"
        }
      ]
    },
    {
      "name": "list",
      "params": [
        {
          "$ref": "#/components/params/uri"
        },
        {
          "$ref": "#/components/params/params"
        }
      ]
    }
  ],
  "components": {
    "params": {
      "uri": {
        "name": "uri",
        "required": true,
        "schema": {
          "type": "string",
          "format": "uri"
        }
      },
      "params": {
        "name": "params",
        "required": true,
        "schema": {
          "type": "object"
        }
      }
    }
  }
}
